<?xml version="1.0" encoding="utf-8"?>
<!DOCTYPE hibernate-mapping PUBLIC "-//Hibernate/Hibernate Mapping DTD 3.0//EN"
"http://hibernate.sourceforge.net/hibernate-mapping-3.0.dtd">
<!-- 
    Mapping file autogenerated by MyEclipse Persistence Tools
-->
<hibernate-mapping>
    <class name="com.kybaby.newbussiness.doctoroperateflow.domain.HealthPlanRemindIssued" table="health_plan_remind_issued" catalog="kybaby">
        <id name="id" type="java.lang.Long">
            <column name="id" />
            <generator class="identity" />
        </id>
        <property name="userId" type="java.lang.Long">
            <column name="userId">
                <comment>用户Id</comment>
            </column>
        </property>
        <property name="orderNum" type="java.lang.String">
            <column name="orderNum" length="30">
                <comment>订单编号</comment>
            </column>
        </property>
        <property name="doTime" type="java.util.Date">
            <column name="do_time">
                <comment>用户执行时间</comment>
            </column>
        </property>
        <property name="createTime" type="java.util.Date">
            <column name="create_time">
                <comment>创建日期</comment>
            </column>
        </property>
        <property name="doNumber" type="java.lang.Long">
            <column name="do_number">
                <comment>用户执行次数</comment>
            </column>
        </property>
        <property name="healthPlanId" type="java.lang.Long">
            <column name="healthPlanId">
                <comment>计划Id</comment>
            </column>
        </property>
        <property name="healthPathId" type="java.lang.Long">
            <column name="healthPathId">
                <comment>健康路径id</comment>
            </column>
        </property>
    </class>
</hibernate-mapping>
