<?xml version="1.0" encoding="utf-8"?>
<!DOCTYPE hibernate-mapping PUBLIC "-//Hibernate/Hibernate Mapping DTD 3.0//EN"
"http://hibernate.sourceforge.net/hibernate-mapping-3.0.dtd">
<!-- 
    Mapping file autogenerated by MyEclipse Persistence Tools
-->
<hibernate-mapping>
    <class name="com.kybaby.operationbussiness.investigation.domain.InvestigationMessage" table="operabuss_investigation_message" catalog="kybaby">
        <id name="id" type="java.lang.Long">
            <column name="id" />
            <generator class="identity" />
        </id>
        <property name="ipAddress" type="java.lang.String">
            <column name="ip_address" length="50">
                <comment>IP地址</comment>
            </column>
        </property>
        <property name="userCode" type="java.lang.String">
            <column name="user_code" length="50">
                <comment>用户序列号 取当前时间精确到毫秒级</comment>
            </column>
        </property>
        <property name="userName" type="java.lang.String">
            <column name="user_name" length="20">
                <comment>用户昵称</comment>
            </column>
        </property>
        <property name="messageContent" type="java.lang.String">
            <column name="message_content" length="500">
                <comment>留言内容</comment>
            </column>
        </property>
        <property name="optTime" type="java.lang.String">
            <column name="opt_time" length="20">
                <comment>操作时间</comment>
            </column>
        </property>
        <property name="isShow" type="java.lang.String">
            <column name="is_show" length="10">
                <comment>0：不显示   1：在公众号中显示   2：前端评论显示</comment>
            </column>
        </property>
    </class>
</hibernate-mapping>
